gascomp/__init__.py
gascomp/eos_bwr/__init__.py
gascomp/eos_bwr/calc.py
gascomp/eos_bwr/data.py
gascomp/eos_bwr/reference.py
gascomp-1.0.9.dist-info/LICENSE
gascomp-1.0.9.dist-info/METADATA
gascomp-1.0.9.dist-info/WHEEL
gascomp-1.0.9.dist-info/top_level.txt
gascomp-1.0.9.dist-info/RECORD
