Metadata-Version: 2.1
Name: gascomp
Version: 1.0.9
Summary: GasComp
Home-page: UNKNOWN
Author: Michael Fischer
Author-email: mfischer.sw@gmail.com
License: UNKNOWN
Project-URL: Source, https://github.com/mfischersw/GasComp/
Platform: UNKNOWN
Requires-Python: >=3.6, <4
License-File: LICENSE
